<?xml version="1.0"?>
<Results version="1.0">
<ReportNode type="testrun">
<ReportNode type="Iteration">
<ReportNode type="Action">
<ReportNode type="Step">
<Data>
    <Name>SystemUtil.Run "iexplore.exe",3</Name>
    <StartTime>2019-03-08 22:12:30</StartTime>
    <Result>Done</Result>
    <Extension>
      <IconKey>f5e022defa95438f84e2fd9c153ff5f1</IconKey>
      <IsPlainTextNodeName>True</IsPlainTextNodeName>
    </Extension>
  </Data>
</ReportNode>
<ReportNode type="Step">
<Data>
    <Name>Run Error</Name>
    <Description>General run error.&lt;BR/&gt;Function file: C:\UFT Framework\iLab\Job Application\Job Application scripts\LIB\iLab Functions.qfl&lt;BR/&gt;Line (44): &amp;quot; 	Browser(&amp;quot;Home Page - iLAB&amp;quot;).Sync&amp;quot;.</Description>
    <StartTime>2019-03-08 22:12:38</StartTime>
    <Result>Failed</Result>
    <Extension>
      <StackTrace>
        <StackFrame>
          <ModuleName><![CDATA[FuncLibExecutableUnitName]]></ModuleName>
          <FileName><![CDATA[C:\UFT Framework\iLab\Job Application\Job Application scripts\LIB\iLab Functions.qfl]]></FileName>
          <Language><![CDATA[VBScript - script block]]></Language>
          <FunctionName><![CDATA[Open_Website]]></FunctionName>
          <Scripts><![CDATA[Browser("Home Page - iLAB").Sync]]></Scripts>
          <LineNo><![CDATA[44]]></LineNo>
        </StackFrame>
        <StackFrame>
          <ModuleName><![CDATA[Action1]]></ModuleName>
          <FileName><![CDATA[Action1]]></FileName>
          <Language><![CDATA[VBScript global code]]></Language>
          <FunctionName><![CDATA[VBScript global code]]></FunctionName>
          <Scripts><![CDATA[Open_Website]]></Scripts>
          <LineNo><![CDATA[1]]></LineNo>
        </StackFrame>
      </StackTrace>
      <IconKey>dd8711ae9a7b42a8ad739de8db09cfd4</IconKey>
      <IsPlainTextNodeName>True</IsPlainTextNodeName>
      <MergeIsErrorIcon>True</MergeIsErrorIcon>
    </Extension>
  </Data>
</ReportNode>
<ReportNode type="Step">
<Data>
    <Name>Stop Run</Name>
    <Description>Run stopped by user.</Description>
    <StartTime>2019-03-08 22:12:54</StartTime>
    <Result>Information</Result>
    <Extension>
      <IconKey>ad323e29f29d4a7f92c24abbbd514ccf</IconKey>
      <IsPlainTextNodeName>True</IsPlainTextNodeName>
    </Extension>
  </Data>
</ReportNode>
<Data>
    <Name>Action1</Name>
    <Description />
    <StartTime>2019-03-08 22:12:24</StartTime>
    <Duration>30</Duration>
    <Result>Failed</Result>
    <InputParameters />
    <Extension>
      <IconKey>a362a2e4bca24de8b62404093a471219</IconKey>
      <IsPlainTextNodeName>True</IsPlainTextNodeName>
    </Extension>
  </Data>
</ReportNode>
<Data>
    <Name>Action0</Name>
    <Description />
    <StartTime>2019-03-08 22:12:24</StartTime>
    <Duration>30</Duration>
    <Result>Failed</Result>
    <Extension>
      <IconKey>9883ed783dbb4f07a522e4df251f93a9</IconKey>
      <IsPlainTextNodeName>True</IsPlainTextNodeName>
    </Extension>
    <Index>1</Index>
    <TestedApplications />
  </Data>
</ReportNode>
<Data>
    <Name>iLab script</Name>
    <ToolName>HPE Unified Functional Testing</ToolName>
    <ToolVersion>14.1</ToolVersion>
    <Description />
    <StartTime>2019-03-08 22:12:19</StartTime>
    <Duration>35</Duration>
    <Result>Failed</Result>
    <InputParameters />
    <Extension>
      <IconKey>315c154dde7548c89a7ba2fcdac92f3a</IconKey>
      <IsPlainTextNodeName>True</IsPlainTextNodeName>
    </Extension>
    <Environment>
      <Timezone>+02:00:00</Timezone>
      <Locale>English (South Africa)</Locale>
      <User>SBICZA01\A230778</User>
      <CpuInfo>Intel(R) Core(TM) i5-5300U CPU @ 2.30GHz</CpuInfo>
      <NumberOfCores>4</NumberOfCores>
      <TotalMemory>3499</TotalMemory>
      <HostName>za.sbicdirectory.com\00620JNBSGB168L</HostName>
      <OSInfo>Windows 7 Service Pack 1 (x86)</OSInfo>
    </Environment>
    <TestedApplications />
    <Links>
      <Link type="DataTable" reference="Default.xls" displayname="Default Data Table" />
    </Links>
  </Data>
</ReportNode>
<GeneralInfo>
    <ResultName>Res11</ResultName>
    <RunStartTime>2019-03-08 22:12:19</RunStartTime>
    <Timezone>+02:00:00</Timezone>
    <OrchestrationToolName>HPE Unified Functional Testing</OrchestrationToolName>
    <OrchestrationToolVersion>14.1</OrchestrationToolVersion>
  </GeneralInfo>
</Results>